amf_rotary_valve/__init__.py
amf_rotary_valve/__main__.py
amf_rotary_valve/device.py
amf_rotary_valve/util.py
amf_rotary_valve-0.2.0.dist-info/METADATA
amf_rotary_valve-0.2.0.dist-info/WHEEL
amf_rotary_valve-0.2.0.dist-info/top_level.txt
amf_rotary_valve-0.2.0.dist-info/RECORD
