Metadata-Version: 2.1
Name: amf-rotary-valve
Version: 0.2.0
Summary: A Python package that provides control of AMF rotary valves
License: EUPL-1.2
Project-URL: repository, https://github.com/slietar/amf-rotary-valve
Requires-Python: >=3.11
Requires-Dist: pyserial (<4,>=3.5)
